claudette_pydantic/__init__.py
claudette_pydantic/_modidx.py
claudette_pydantic/struct.py
claudette_pydantic-0.0.1.dist-info/LICENSE
claudette_pydantic-0.0.1.dist-info/METADATA
claudette_pydantic-0.0.1.dist-info/WHEEL
claudette_pydantic-0.0.1.dist-info/entry_points.txt
claudette_pydantic-0.0.1.dist-info/top_level.txt
claudette_pydantic-0.0.1.dist-info/RECORD
