Metadata-Version: 2.1
Name: claudette-pydantic
Version: 0.0.1
Home-page: https://github.com/tom-pollak/claudette-pydantic
Author: Tom Pollak
Author-email: tompollak100@gmail.com
License: Apache Software License 2.0
Classifier: Development Status :: 4 - Beta
Classifier: Intended Audience :: Developers
Classifier: Natural Language :: English
Classifier: Programming Language :: Python :: 3.7
Classifier: Programming Language :: Python :: 3.8
Classifier: Programming Language :: Python :: 3.9
Classifier: Programming Language :: Python :: 3.10
Classifier: License :: OSI Approved :: Apache Software License
Requires-Python: >=3.7
License-File: LICENSE
Requires-Dist: claudette
Requires-Dist: pydantic
Provides-Extra: dev
